<?xml version="1.0"?>
<arts format="ascii" version="1">
<SingleScatteringData version="2"><String>"macroscopically_isotropic"</String>
<String>"T-matrix calculation for a cylindrical particle, with diameter_volume_equ = 100um and aspect ratio = 2."</String>
<Vector nelem="2">
230000000000
240000000000
</Vector>
<Vector nelem="3">
220
250
270
</Vector>
<Vector nelem="19">
0
10
20
30
40
50
60
70
80
90
100
110
120
130
140
150
160
170
180
</Vector>
<Vector nelem="0">
</Vector>
<Tensor7 nlibraries="2" nvitrines="3" nshelves="19" nbooks="1" npages="1" nrows="1" ncols="6">
1.67384572240904e-12 0 1.66056062667366e-12 1.66056062667366e-12 0 1.64727553138305e-12
1.64817737278393e-12 -2.48409710088452e-14 1.63489711839649e-12 1.63470836433165e-12 -2.39620836462215e-20 1.62162183462774e-12
1.5743053064773e-12 -9.62580162496853e-14 1.56103966334788e-12 1.55806869572529e-12 -9.48596198723771e-20 1.54557145157486e-12
1.46122455804436e-12 -2.05336376497287e-13 1.44798352586266e-12 1.43334851304388e-12 -2.09355945748603e-19 1.42181228238299e-12
1.32263687618774e-12 -3.38504595792683e-13 1.3094307361544e-12 1.26491464361879e-12 -3.60834160440132e-19 1.25468029300255e-12
1.17520417836618e-12 -4.7927603510957e-13 1.16204340870834e-12 1.05858885936526e-12 -5.38381212186476e-19 1.04995566729015e-12
1.03644959078187e-12 -6.10341201279961e-13 1.02334462117375e-12 8.21383413886105e-13 -7.26304770011727e-19 8.14599857341448e-13
9.22586715760023e-13 -7.15730614975014e-13 9.09547520318514e-13 5.61196425350467e-13 -9.04725315768592e-19 5.56452772829223e-13
8.46558109772702e-13 -7.82767644077561e-13 8.33593663516049e-13 2.86487917440899e-13 -1.05151330821619e-18 2.83910834093212e-13
8.16525163342198e-13 -8.0356953022503e-13 8.0364280949233e-13 5.9566609319227e-15 -1.14544503586066e-18 5.60594065653382e-15
8.34982145568682e-13 -7.75924242352805e-13 8.22186937901195e-13 -2.71764607449843e-13 -1.17004507921257e-18 -2.6989715593176e-13
8.98579586657481e-13 -7.03458332006219e-13 8.85873680135834e-13 -5.38381984613838e-13 -1.11728827304467e-18 -5.34371549888505e-13
9.9865022655386e-13 -5.95102844209254e-13 9.86032389655462e-13 -7.86172375592993e-13 -9.90241346682124e-19 -7.80158172983588e-13
1.12234708247191e-12 -4.63947938138979e-13 1.10981239597334e-12 -1.00817070326027e-12 -8.03871540387426e-19 -1.00035119322355e-12
1.25423737710691e-12 -3.25642608351371e-13 1.24177716773638e-12 -1.19831287862678e-12 -5.83609705944099e-19 -1.18893938371599e-12
1.37815376140245e-12 -1.96538138766897e-13 1.36575579663133e-12 -1.35153863016613e-12 -3.61745135084587e-19 -1.34090758460117e-12
1.4790871504647e-12 -9.17909841543242e-14 1.46673609531674e-12 -1.46386068308902e-12 -1.72230359702326e-19 -1.45230476214618e-12
1.5449120295385e-12 -2.36341997398016e-14 1.53259014044012e-12 -1.53240787355394e-12 -4.48638083543209e-20 -1.52028625475835e-12
1.56776160849752e-12 0 1.55544961564055e-12 -1.55544961564055e-12 0 -1.54313762322207e-12
1.67803429201575e-12 0 1.66468854816001e-12 1.66468854816001e-12 0 1.65134280475006e-12
1.65230218058988e-12 -2.49023688292272e-14 1.63896130520584e-12 1.63877208724472e-12 6.44752295138701e-19 1.62562581049211e-12
1.57824657242713e-12 -9.64959418029433e-14 1.56492038987776e-12 1.56194212025481e-12 2.4969618224568e-18 1.54938780323798e-12
1.4648847380663e-12 -2.05843954057877e-13 1.45158330297598e-12 1.43691231781964e-12 5.32148259095969e-18 1.42532337558393e-12
1.32595230881041e-12 -3.39341440773457e-13 1.31268595769019e-12 1.26806043537086e-12 8.76143084503285e-18 1.2577792818063e-12
1.17815242695064e-12 -4.80461040613054e-13 1.16493169303603e-12 1.06122279992406e-12 1.23853094223096e-17 1.05255007245833e-12
1.03905160851468e-12 -6.1185048266088e-13 1.02588697483672e-12 8.23429174145799e-13 1.57431045263273e-17 8.16614478481279e-13
9.24903649966423e-13 -7.17500792320079e-13 9.11805140332341e-13 5.6259736604724e-13 1.84235007645457e-17 5.57831835500459e-13
8.48683253927146e-13 -7.84703951899683e-13 8.35659886814198e-13 2.87208450565785e-13 2.01045428715211e-17 2.84619326630997e-13
8.18572163490346e-13 -8.05557646564561e-13 8.05631316446387e-13 5.98279761953571e-15 2.05913861625146e-17 5.63014708431856e-15
8.37070997152808e-13 -7.77844301360635e-13 8.24217746192863e-13 -2.72425471605036e-13 1.98369164955847e-17 -2.70549875807734e-13
9.00822172492375e-13 -7.05199370338449e-13 8.8805868005139e-13 -5.39701961322374e-13 1.79435668904462e-17 -5.3567364792851e-13
1.00113713504748e-12 -5.96575944023673e-13 9.88462160219885e-13 -7.8810454527476e-13 1.51471777355506e-17 -7.82063360785906e-13
1.12513722622331e-12 -4.65096549025969e-13 1.11254582234026e-12 -1.0106510296001e-12 1.17858753366847e-17 -1.00279633509079e-12
1.25735154869974e-12 -3.26448914202372e-13 1.2448349968624e-12 -1.20126246243383e-12 8.2584405484481e-18 -1.19184672160612e-12
1.381572772892e-12 -1.97024826062114e-13 1.36911877784389e-12 -1.35486620061777e-12 4.97741350840369e-18 -1.34418719419825e-12
1.48275466788006e-12 -9.20183033300169e-14 1.4703478170951e-12 -1.46746524250979e-12 2.32227194071242e-18 -1.45585715732142e-12
1.54874169267467e-12 -2.3692732242328e-14 1.53636415356666e-12 -1.53618143265074e-12 5.97559814631014e-19 -1.5240050784916e-12
1.57164756975722e-12 0 1.55927997625928e-12 -1.55927997625928e-12 0 -1.5469123832008e-12
1.67966855760928e-12 0 1.66629905816292e-12 1.66629905816292e-12 0 1.65292955916273e-12
1.65391156498617e-12 -2.49263273950594e-14 1.64054694468079e-12 1.64035754569174e-12 1.41376372179275e-18 1.62718786627041e-12
1.57978433553566e-12 -9.65887839772459e-14 1.56643444015254e-12 1.56345332106813e-12 5.4775256064723e-18 1.55087664877444e-12
1.46631281830127e-12 -2.06042015833359e-13 1.45298772406967e-12 1.43830270161807e-12 1.16819099919782e-17 1.4266931122755e-12
1.32724586806638e-12 -3.39667979858523e-13 1.31395593324588e-12 1.26928770954331e-12 1.92520396503405e-17 1.25898822306278e-12
1.17930271497781e-12 -4.80923422197541e-13 1.16605849442923e-12 1.06225035436679e-12 2.7247673004189e-17 1.05356214039034e-12
1.0400668061945e-12 -6.12439378902041e-13 1.0268788039209e-12 8.24227233904994e-13 3.46832454000599e-17 8.17400340164842e-13
9.25807620311778e-13 -7.18191465352617e-13 9.12685879647911e-13 5.63143841770512e-13 4.06515552923189e-17 5.58369740242625e-13
8.49512399781604e-13 -7.85459420478615e-13 8.3646595628072e-13 2.8748946878981e-13 4.44349141170684e-17 2.84895626631301e-13
8.19370824401467e-13 -8.063333034138e-13 8.06407069096426e-13 5.99291327844205e-15 4.55899454506105e-17 5.63950408492706e-15
8.37885985243842e-13 -7.78593381390149e-13 8.25010002883737e-13 -2.72683360419286e-13 4.39963487899788e-17 -2.70804577798117e-13
9.01697130655303e-13 -7.05878586779151e-13 8.88911086604919e-13 -5.40216962813491e-13 3.98650771012835e-17 -5.36181650389097e-13
1.0021073958716e-12 -5.97150614749556e-13 9.89410045531317e-13 -7.88858345506672e-13 3.37066874107481e-17 -7.82806597018899e-13
1.12622576430713e-12 -4.65544621328866e-13 1.11361215021563e-12 -1.01161864055745e-12 2.62653679607191e-17 -1.00375016982118e-12
1.25856646921862e-12 -3.2676344620796e-13 1.24602785453946e-12 -1.20241310203029e-12 1.8427779419701e-17 -1.1929808196659e-12
1.38290658794101e-12 -1.97214674404438e-13 1.37043065275982e-12 -1.35616426480897e-12 1.11180773682193e-17 -1.34546647886452e-12
1.48418540344138e-12 -9.2106975390702e-14 1.4717567047495e-12 -1.46887133677659e-12 5.19125803805507e-18 -1.4572428260127e-12
1.55023566604928e-12 -2.37155642499594e-14 1.53783633627335e-12 -1.53765343828302e-12 1.33642854131284e-18 -1.52545565170128e-12
1.573163499546e-12 0 1.56077413478448e-12 -1.56077413478448e-12 0 -1.54838477046281e-12
1.99255001781958e-12 0 1.97666594174016e-12 1.97666594174016e-12 0 1.96078186640173e-12
1.96192966946913e-12 -2.95491476102865e-14 1.94605187892093e-12 1.94582749579791e-12 -1.43768250032684e-19 1.93018048916477e-12
1.87380990677555e-12 -1.14490650118351e-13 1.85795108491998e-12 1.85441967291839e-12 -5.60353451954217e-19 1.8394761802487e-12
1.73892958562886e-12 -2.44190256258446e-13 1.72310271062088e-12 1.70570978313583e-12 -1.20669557282485e-18 1.6919134676135e-12
1.57363864240346e-12 -4.02467720433945e-13 1.55785705257479e-12 1.50496378784238e-12 -2.01474411264671e-18 1.49272130711536e-12
1.39780442973199e-12 -5.69683790699925e-13 1.38208171235931e-12 1.25919236521565e-12 -2.8971624486236e-18 1.24886053794188e-12
1.23229990972469e-12 -7.25243236401881e-13 1.21664958136189e-12 9.76824258962079e-13 -3.75538218006703e-18 9.68699068966243e-13
1.09641225334154e-12 -8.50175867049643e-13 1.08084723158954e-12 6.67331555842304e-13 -4.4897045781674e-18 6.61639344914011e-13
1.00550913981366e-12 -9.29458805950752e-13 9.90041039086875e-13 3.40833307204054e-13 -5.01069967647064e-18 3.37724398685917e-13
9.69251347508946e-13 -9.53791993599721e-13 9.53889660413118e-13 7.70287073636144e-15 -5.25067222402027e-18 7.24775367832012e-15
9.90554935433717e-13 -9.2062415268518e-13 9.75306182988127e-13 -3.2179912731705e-13 -5.17359848040208e-18 -3.1961103126701e-13
1.06540004179476e-12 -8.34332648327533e-13 1.05026698720095e-12 -6.37849562585196e-13 -4.78183131074401e-18 -6.33108623457631e-13
1.18347306059195e-12 -7.05570847727645e-13 1.16845408123972e-12 -9.31334879953839e-13 -4.11811279254843e-18 -9.24207628687664e-13
1.32952993514408e-12 -5.49895499846698e-13 1.31461863617874e-12 -1.19406634803938e-12 -3.26202933697795e-18 -1.18478970582408e-12
1.48529177247395e-12 -3.85863086988878e-13 1.47047690399053e-12 -1.41894008279893e-12 -2.32090834649987e-18 -1.4078137084489e-12
1.63163615722515e-12 -2.3283183427136e-13 1.61690186854366e-12 -1.60004791009985e-12 -1.41612717577035e-18 -1.58742494925264e-12
1.75082978382557e-12 -1.08723752081948e-13 1.73615621559503e-12 -1.73274807030416e-12 -6.66685877257415e-19 -1.71902460225571e-12
1.82855785124441e-12 -2.79912147249692e-14 1.81392203290587e-12 -1.81370601868661e-12 -1.72494020685283e-19 -1.79930949866059e-12
1.85553822227304e-12 0 1.84091521221196e-12 -1.84091521221196e-12 0 -1.82629220288053e-12
1.99717340695687e-12 0 1.98122208160939e-12 1.98122208160939e-12 0 1.96527075700443e-12
1.96648253477086e-12 -2.96168347476816e-14 1.95053752764612e-12 1.95031263371671e-12 7.48240614490644e-19 1.93459937498067e-12
1.87815977058566e-12 -1.14752922523133e-13 1.86223383046799e-12 1.85869437884918e-12 2.89663947625885e-18 1.84368759328874e-12
1.74296857376875e-12 -2.44749686384863e-13 1.7270747449946e-12 1.70964221764269e-12 6.16940918660236e-18 1.69578743488042e-12
1.57729635328861e-12 -4.03389858688119e-13 1.56144804078954e-12 1.5084343369094e-12 1.01488234631911e-17 1.49613992570176e-12
1.40105602244543e-12 -5.70989232238502e-13 1.38526687969113e-12 1.2620976739649e-12 1.4331393989587e-17 1.25172195482332e-12
1.23516845104001e-12 -7.26905405502653e-13 1.21945205874115e-12 9.79080493626431e-13 1.81943468962629e-17 9.70920696716283e-13
1.09896513414268e-12 -8.52124704357494e-13 1.08333446959595e-12 6.68876782830194e-13 2.12628349537452e-17 6.63160203652563e-13
1.00784914081661e-12 -9.3158977595295e-13 9.9231587059123e-13 3.41628941675583e-13 2.3168687744223e-17 3.38506537705025e-13
9.71503594957819e-13 -9.55979170445545e-13 9.56077252794487e-13 7.73420794343527e-15 2.3693268859177e-17 7.27676655848542e-15
9.92851455864774e-13 -9.22735675470599e-13 9.77538589362558e-13 -3.22523232508288e-13 2.2789752080712e-17 -3.2032633251815e-13
1.06786385227576e-12 -8.36246610880051e-13 1.05266723345647e-12 -6.39297763362405e-13 2.05832896152864e-17 -6.34537270904372e-13
1.18620370656287e-12 -7.07189713173801e-13 1.17112170138942e-12 -9.33455023808686e-13 1.73505641159994e-17 -9.26298169618019e-13
1.33259213626699e-12 -5.51157382638739e-13 1.31761831677771e-12 -1.19678764444388e-12 1.34826434595012e-17 -1.18747234628234e-12
1.48870840784159e-12 -3.86748674518296e-13 1.47383146921583e-12 -1.42217562041828e-12 9.43662806515969e-18 -1.41100279832812e-12
1.63538627977486e-12 -2.33366261846047e-13 1.62059029591543e-12 -1.60369740773293e-12 5.682232966483e-18 -1.59102169432236e-12
1.75485176860562e-12 -1.08973330199812e-13 1.74011678698189e-12 -1.73670076880121e-12 2.64929119497994e-18 -1.72291991161616e-12
1.83275721710114e-12 -2.80554724904431e-14 1.81806016024165e-12 -1.81784364699914e-12 6.81419391914126e-19 -1.80338690203675e-12
1.85979917484023e-12 0 1.8451149855385e-12 -1.8451149855385e-12 0 -1.83043079696786e-12
1.99896158930151e-12 0 1.98298414096645e-12 1.98298414096645e-12 0 1.96700669337453e-12
1.96824343585603e-12 -2.96430127608638e-14 1.95227231853878e-12 1.95204722704507e-12 1.75136087108513e-18 1.93630823263138e-12
1.87984214372211e-12 -1.14854355290927e-13 1.86389013188922e-12 1.86034757082783e-12 6.7842579775792e-18 1.84531619897241e-12
1.74453069134237e-12 -2.44966039718952e-13 1.72861085522597e-12 1.71116301231846e-12 1.44643708143241e-17 1.69728551755903e-12
1.57871098498526e-12 -4.037464764738e-13 1.56283675556931e-12 1.50977647210054e-12 2.38277245157054e-17 1.49746188774382e-12
1.40231356280852e-12 -5.7149406912405e-13 1.38649861944855e-12 1.26322118240156e-12 3.37064401489325e-17 1.25282841219405e-12
1.23627782518322e-12 -7.27548172268721e-13 1.22053577367269e-12 9.79952964670347e-13 4.28790111053078e-17 9.71779722731564e-13
1.09995240888465e-12 -8.5287829705047e-13 1.08429624985357e-12 6.6947428174775e-13 5.02244505973798e-17 6.63748233843329e-13
1.00875406640094e-12 -9.32413762562057e-13 9.93195486799851e-13 3.41936568157773e-13 5.48599294486545e-17 3.38808917882943e-13
9.72374558128271e-13 -9.56824853894251e-13 9.5692310776865e-13 7.74629920777865e-15 5.62447331743964e-17 7.28794963386515e-15
9.93739506011833e-13 -9.23552071302217e-13 9.7840174287189e-13 -3.22803228439791e-13 5.42387813182299e-17 -3.20602915330042e-13
1.0688165498571e-12 -8.36986591006747e-13 1.05359524939418e-12 -6.39857703406205e-13 4.9110545974513e-17 -6.35089623799464e-13
1.18725953308773e-12 -7.07815577342852e-13 1.17215305678483e-12 -9.34274724504008e-13 4.14958905895993e-17 -9.2710638100683e-13
1.3337761073071e-12 -5.51645217355572e-13 1.31877801424782e-12 -1.19783972223229e-12 3.23151773462099e-17 -1.18850941967977e-12
1.4900293642907e-12 -3.87091025555495e-13 1.47512832817553e-12 -1.42342646628226e-12 2.26603021412437e-17 -1.41223561450999e-12
1.63683612310169e-12 -2.33572855998371e-13 1.62201618834255e-12 -1.6051082512731e-12 1.36657977061865e-17 -1.592412060289e-12
1.75640667973382e-12 -1.09069808038652e-13 1.74164785736854e-12 -1.73822879585783e-12 6.37880798840154e-18 -1.72442566095135e-12
1.83438068043126e-12 -2.80803119254448e-14 1.81965985119146e-12 -1.8194431450496e-12 1.64182845169387e-18 -1.80496302138173e-12
1.86144643930126e-12 0 1.84673850079286e-12 -1.84673850079286e-12 0 -1.8320305630162e-12
</Tensor7>
<Tensor5 nshelves="2" nbooks="3" npages="1" nrows="1" ncols="1">
2.33195273714861e-11
3.12977070496757e-11
4.04072118198905e-11
2.66427256866622e-11
3.52558482917727e-11
4.48715197520321e-11
</Tensor5>
<Tensor5 nshelves="2" nbooks="3" npages="1" nrows="1" ncols="1">
9.69021716861781e-12
1.76343383093314e-11
2.67305533850048e-11
1.04638906708802e-11
1.90395393800221e-11
2.86407192089967e-11
</Tensor5>
</SingleScatteringData>
</arts>
