<?xml version="1.0"?>
<arts format="ascii" version="1">
<Array type="Vector" nelem="19">
<Vector nelem="1">
   2.0030970e+13
</Vector>
<Vector nelem="1">
   2.0406761e+13
</Vector>
<Vector nelem="1">
   2.0734488e+13
</Vector>
<Vector nelem="1">
   2.1129893e+13
</Vector>
<Vector nelem="1">
   2.1488868e+13
</Vector>
<Vector nelem="1">
   2.1993829e+13
</Vector>
<Vector nelem="1">
   2.2521412e+13
</Vector>
<Vector nelem="1">
   2.6984773e+13
</Vector>
<Vector nelem="1">
   3.0869817e+13
</Vector>
<Vector nelem="1">
   3.6742616e+13
</Vector>
<Vector nelem="1">
   4.0899306e+13
</Vector>
<Vector nelem="1">
   4.4682848e+13
</Vector>
<Vector nelem="1">
   6.5741561e+13
</Vector>
<Vector nelem="1">
   6.6262264e+13
</Vector>
<Vector nelem="1">
   6.7125061e+13
</Vector>
<Vector nelem="1">
   6.8073144e+13
</Vector>
<Vector nelem="1">
   7.0797063e+13
</Vector>
<Vector nelem="1">
   7.5437287e+13
</Vector>
<Vector nelem="1">
   7.9961400e+13
</Vector>
</Array>
</arts>
