<?xml version="1.0"?>
<arts format="ascii" version="1">
<Array nelem="3" type="GriddedField1">
<GriddedField1 name="Backend channel response function">
<Vector name="Frequency" nelem="25">
-7196704243712
-6641739104256
-6358514532352
-6071351508992
-5484908118016
-4881704288256
-4261014405120
-3622075105280
-3295502401536
-2964055916544
-2286092812288
-1587279822848
-866627092480
-123094433792
  257597374464
  644425449472
  1437106962432
  2256212590592
  3103084511232
  3979157176320
  4428618792960
  4885974089728
  5825171030016
  6798526382080
  7807919194112
</Vector>
<Vector nelem="25">
  0
  0.00049029
  0.00098058
  0.0015689
  0.0027456
  0.015199
  0.037851
  0.059031
  0.058639
  0.053834
  0.048049
  0.04295
  0.061287
  0.087958
  0.098058
  0.093744
  0.083252
  0.072269
  0.064719
  0.056089
  0.037458
  0.021181
  0.001667
  0.00098058
  0
</Vector>
</GriddedField1>
<GriddedField1 name="Backend channel response function">
<Vector name="Frequency" nelem="38">
-3472277635072
-3296238501888
-3117470973952
-2935912136704
-2844061073408
-2751488589824
-2564145807360
-2373799903232
-2180385865728
-1983826100224
-1884343500800
-1784045109248
-1580961103872
-1374492295168
-1164554797056
-951056334848
-842943954944
-733910925312
-513020002304
-288289193984
-59611545600
  173107314688
  291019685888
  409986924544
  651134238720
  896664600576
  1146699644928
  1401361006592
  1530474266624
  1660789194752
  1925110038528
  2194466144256
  2469002215424
  2748865052672
  2890848534528
  3034220331008
  3325223239680
  3622049939456
</Vector>
<Vector nelem="38">
  0
  0.00038516
  0.00070612
  0.0010271
  0.0017974
  0.0024393
  0.0054564
  0.011298
  0.017717
  0.020542
  0.020927
  0.021505
  0.02388
  0.028887
  0.032289
  0.035948
  0.039094
  0.04256
  0.051162
  0.056939
  0.061433
  0.062845
  0.064193
  0.06368
  0.057581
  0.05726
  0.057196
  0.049878
  0.042046
  0.034921
  0.019707
  0.0081525
  0.0026961
  0.0016048
  0.0010913
  0.00057774
  0.00057774
  0
</Vector>
</GriddedField1>
<GriddedField1 name="Backend channel response function">
<Vector name="Frequency" nelem="67">
-152074457186304
-149329100668928
-146530426159104
-143676923707392
-140766882037760
-137798623428608
-134770436603904
-131680442515456
-128526695006208
-125307281473536
-122020087988224
-118662967066624
-115233637007360
-111729715445760
-108148820017152
-104488333475840
-100745605021696
-96917849636864
-93002080976896
-88995212034048
-84894122246144
-80695321952256
-76395355045888
-71990530539520
-67476922564608
-62850538143744
-58106948091904
-53241790332928
-48250233028608
-43127310123008
-37867820679168
-32466194661376
-26916526489600
-21212675702784
-15348199849984
-9316153163776
-3109321441280
  3280180609024
  9860338941952
  16639877709824
  23628091490304
  30834576850944
  38269936992256
  45945144213504
  53871909011456
  62062982070272
  70531751608320
  79292444704768
  88360563507200
  97752616796160
  107486019321856
  117580098437120
  128055087464448
  138932897447936
  150237251371008
  161993851928576
  174230213754880
  186976535838720
  200265164652544
  214131667894272
  228614431834112
  267802854293504
  311890022498304
  361855457427456
  418958792458240
  484847281766400
  561717062926336
</Vector>
<Vector nelem="67">
  0
  0.0024641
  0.002573
  0.0029231
  0.0034062
  0.0040223
  0.0047712
  0.0054597
  0.0064504
  0.0074046
  0.008673
  0.010159
  0.011294
  0.013178
  0.014495
  0.015787
  0.017285
  0.018638
  0.019822
  0.021078
  0.022045
  0.02266
  0.023059
  0.023796
  0.023893
  0.023917
  0.023796
  0.023687
  0.023796
  0.023397
  0.023784
  0.023289
  0.023905
  0.023675
  0.023337
  0.02318
  0.022951
  0.023265
  0.023277
  0.023385
  0.022866
  0.021887
  0.020317
  0.018964
  0.018095
  0.017491
  0.016996
  0.016114
  0.015437
  0.015353
  0.015618
  0.015872
  0.015026
  0.013988
  0.013045
  0.012176
  0.011355
  0.01075
  0.010146
  0.010376
  0.0098083
  0.0077789
  0.0057376
  0.0037083
  0.0020777
  0.0010387
  0
</Vector>
</GriddedField1>
</Array>
</arts>
